LICENSE
README.md
setup.py
pythemer.egg-info/PKG-INFO
pythemer.egg-info/SOURCES.txt
pythemer.egg-info/dependency_links.txt
pythemer.egg-info/entry_points.txt
pythemer.egg-info/requires.txt
pythemer.egg-info/top_level.txt
themer/__init__.py
themer/__main__.py
themer/apps.py
themer/elevate.py
themer/library.py
themer/logger.py
themer/recovery.py
themer/theme.py
themer/typedef.py