Metadata-Version: 2.1
Name: pythemer
Version: 1.0.2
Summary: A WIP theme engine for macOS, written in Python.
Home-page: https://github.com/pythemer/themer
Author: Jaidan
Author-email: ajaidan0@gmail.com
License: JL
Download-URL: https://github.com/pythemer/themer/archive/1.0.0.tar.gz
Keywords: theme,themes,macos,mac,icon
Platform: UNKNOWN
Classifier: Programming Language :: Python :: 2.7
Classifier: Programming Language :: Python :: 3
Classifier: Programming Language :: Python :: 3.7
Requires-Python: >=2.7
License-File: LICENSE
